opbtest/__init__.py
opbtest/opbtestassertions.py
opbtest/opbtestcase.py
opbtest/opbtestmockable.py
opbtest-0.1.dist-info/LICENSE
opbtest-0.1.dist-info/METADATA
opbtest-0.1.dist-info/WHEEL
opbtest-0.1.dist-info/top_level.txt
opbtest-0.1.dist-info/RECORD
