Metadata-Version: 2.1
Name: opbtest
Version: 0.1
Summary: Open PicoBlaze Assembler Test package
Home-page: https://github.com/wgroeneveld/opbtest
Author: Wouter Groeneveld
Author-email: wouter.groeneveld@kuleuven.be
License: MIT
Platform: UNKNOWN
